{
  "grubDict": {
    "Grub-Crossroads_Acid": "Nimble",
    "Grub-Crossroads_Center": "Grumblewort",
    "Grub-Crossroads_Stag": "Wandering Grub",
    "Grub-Crossroads_Spike": "Mordant the Ancient",
    "Grub-Crossroads_Guarded": "Snaggle",
    "Grub-Greenpath_Cornifer": "Grub-Grub-Grumble",
    "Grub-Greenpath_Journal": "Grub-with-Glee",
    "Grub-Greenpath_MMC": "Grubby Groove Grub",
    "Grub-Greenpath_Stag": "Glitter",
    "Grub-Fog_Canyon": "Grumpshrimp",
    "Grub-Fungal_Bouncy": "Grumpty",
    "Grub-Fungal_Spore_Shroom": "Grumptysnout",
    "Grub-Deepnest_Mimic": "Grumwyrm",
    "Grub-Deepnest_Nosk": "Grumpus",
    "Grub-Deepnest_Spike": "Grounder",
    "Grub-Dark_Deepnest": "Grumblethorn",
    "Grub-Beast's_Den": "Grumbleweed",
    "Grub-Kingdom's_Edge_Oro": "Grubby Little Grub",
    "Grub-Kingdom's_Edge_Camp": "Grub-a-Licious",
    "Grub-Hive_External": "Grub's Grotto",
    "Grub-Hive_Internal": "Grumble Grub",
    "Grub-Basin_Requires_Wings": "Grubberling",
    "Grub-Basin_Requires_Dive": "Tunnel Grub",
    "Grub-Waterways_Main": "Chirp",
    "Grub-Isma's_Grove": "Vengeful Spirit",
    "Grub-Waterways_Requires_Tram": "Upside-Down Grub",
    "Grub-City_of_Tears_Left": "Radiant Grub",
    "Grub-Soul_Sanctum": "Grubblegut the Gluttonous",
    "Grub-Watcher's_Spire": "Glittersnaps",
    "Grub-City_of_Tears_Guarded": "Grubling",
    "Grub-King's_Station": "Grub-in-the-Rough",
    "Grub-Resting_Grounds": "Grublet",
    "Grub-Crystal_Peak_Below_Chest": "Jen Jen",
    "Grub-Crystallized_Mound": "Grubbing",
    "Grub-Crystal_Peak_Spike": "Grubbin",
    "Grub-Crystal_Peak_Mimic": "Royal Grub",
    "Grub-Crystal_Peak_Crushers": "Gumbo",
    "Grub-Crystal_Heart": "Grubber",
    "Grub-Hallownest_Crown": "Cholli",
    "Grub-Howling_Cliffs": "Tootle",
    "Grub-Queen's_Gardens_Stag": "Grumble",
    "Grub-Queen's_Gardens_Marmu": "Grubnose",
    "Grub-Queen's_Gardens_Top": "Grubbster",
    "Grub-Collector_1": "Grub-Tastic!",
    "Grub-Collector_2": "Grubbing Around",
    "Grub-Collector_3": "Grub-a-Doodle-Doo"
  }
}